ro_py/__init__.py
ro_py/accountinformation.py
ro_py/accountsettings.py
ro_py/assets.py
ro_py/badges.py
ro_py/captcha.py
ro_py/catalog.py
ro_py/chat.py
ro_py/client.py
ro_py/economy.py
ro_py/events.py
ro_py/friends.py
ro_py/gamepasses.py
ro_py/gamepersistence.py
ro_py/games.py
ro_py/gender.py
ro_py/groups.py
ro_py/notifications.py
ro_py/presence.py
ro_py/robloxbadges.py
ro_py/robloxdocs.py
ro_py/robloxstatus.py
ro_py/roles.py
ro_py/thumbnails.py
ro_py/trades.py
ro_py/users.py
ro_py/wall.py
ro_py/bases/__init__.py
ro_py/bases/baseasset.py
ro_py/bases/basetrade.py
ro_py/bases/baseuser.py
ro_py/extensions/__init__.py
ro_py/extensions/anticaptcha.py
ro_py/extensions/bots.py
ro_py/extensions/prompt.py
ro_py/extensions/twocaptcha.py
ro_py/utilities/__init__.py
ro_py/utilities/asset_type.py
ro_py/utilities/cache.py
ro_py/utilities/caseconvert.py
ro_py/utilities/clientobject.py
ro_py/utilities/errors.py
ro_py/utilities/pages.py
ro_py/utilities/requests.py
ro_py/utilities/url.py
ro_py-1.2.0.5.dist-info/LICENSE
ro_py-1.2.0.5.dist-info/METADATA
ro_py-1.2.0.5.dist-info/WHEEL
ro_py-1.2.0.5.dist-info/top_level.txt
ro_py-1.2.0.5.dist-info/RECORD
