Metadata-Version: 2.1
Name: ro-py
Version: 1.2.0.5
Summary: ro.py is a Python wrapper for the Roblox web API.
Home-page: https://github.com/rbx-libdev/ro.py
Author: jmkdev and iranathan
Author-email: jmk@jmksite.dev
License: UNKNOWN
Project-URL: Discord, https://discord.gg/RJdW3gt9Ru
Project-URL: Issue Tracker, https://github.com/rbx-libdev/ro.py/issues
Project-URL: GitHub, https://github.com/rbx-libdev/ro.py/
Project-URL: Examples, https://github.com/rbx-libdev/ro.py/tree/main/examples
Platform: UNKNOWN
Classifier: Programming Language :: Python :: 3
Classifier: License :: OSI Approved :: GNU General Public License v3 (GPLv3)
Classifier: Operating System :: OS Independent
Requires-Python: >=3.6
